repgen/__init__.py
repgen/__main__.py
repgen/data/__init__.py
repgen/data/value.py
repgen/report/__init__.py
repgen/report/report.py
repgen/util/__init__.py
repgen/util/extra_operator.py
repgen/util/urllib2_tls.py
cwms_repgen-5.1.6.dist-info/LICENSE.md
cwms_repgen-5.1.6.dist-info/METADATA
cwms_repgen-5.1.6.dist-info/WHEEL
cwms_repgen-5.1.6.dist-info/entry_points.txt
cwms_repgen-5.1.6.dist-info/top_level.txt
cwms_repgen-5.1.6.dist-info/RECORD
