Metadata-Version: 2.1
Name: cwms-repgen
Version: 5.1.6
Summary: This is a partial copy of HEC's (Hydrologic Engineering Center) repgen program.
Home-page: https://github.com/USACE-WaterManagement/repgen5
Author: USACE-HEC
License: MIT
Classifier: Programming Language :: Python :: 3
Classifier: License :: OSI Approved :: MIT License
Classifier: Operating System :: OS Independent
Requires-Python: >=3.8
License-File: LICENSE.md
Requires-Dist: pytz>=2022.1
Requires-Dist: python-dateutil>=2.8.2
Provides-Extra: dev
Requires-Dist: sphinx; extra == "dev"
Requires-Dist: sphinx-rtd-theme; extra == "dev"
Requires-Dist: sphinx-copybutton; extra == "dev"
Requires-Dist: myst-parser; extra == "dev"
Requires-Dist: twine; extra == "dev"
Requires-Dist: wheel; extra == "dev"
